{"version": "1.1.0",
 "packagesDir": ".lake/packages",
 "packages":
 [{"url": "https://github.com/leanprover/verso",
   "type": "git",
   "subDir": null,
   "scope": "",
   "rev": "8ba8c1ee844cd4a4ef1957801780c6e99e469897",
   "name": "verso",
   "manifestFile": "lake-manifest.json",
   "inputRev": "v4.25.1",
   "inherited": false,
   "configFile": "lakefile.lean"},
  {"type": "path",
   "scope": "",
   "name": "Strata",
   "manifestFile": "lake-manifest.json",
   "inherited": false,
   "dir": "../..",
   "configFile": "lakefile.toml"},
  {"url": "https://github.com/leanprover-community/plausible",
   "type": "git",
   "subDir": null,
   "scope": "",
   "rev": "8864a73bf79aad549e34eff972c606343935106d",
   "name": "plausible",
   "manifestFile": "lake-manifest.json",
   "inputRev": "main",
   "inherited": true,
   "configFile": "lakefile.toml"},
  {"url": "https://github.com/acmepjz/md4lean",
   "type": "git",
   "subDir": null,
   "scope": "",
   "rev": "66aefec2852d3e229517694e642659f316576591",
   "name": "MD4Lean",
   "manifestFile": "lake-manifest.json",
   "inputRev": "main",
   "inherited": true,
   "configFile": "lakefile.lean"},
  {"url": "https://github.com/leanprover/subverso",
   "type": "git",
   "subDir": null,
   "scope": "",
   "rev": "7347ddaca36e59238bf1fc210a6bf71dd0bccdd6",
   "name": "subverso",
   "manifestFile": "lake-manifest.json",
   "inputRev": "main",
   "inherited": true,
   "configFile": "lakefile.lean"}],
 "name": "StrataDoc",
 "lakeDir": ".lake"}
